ject/__init__.py
ject/length/__init__.py
ject/oneself/__init__.py
ject/pipe/__init__.py
ject/pipe/predicates/__init__.py
ject-0.0.3.dist-info/WHEEL
ject-0.0.3.dist-info/METADATA
ject-0.0.3.dist-info/RECORD
