Metadata-Version: 2.1
Name: ject
Version: 0.0.3
Summary: functional extensions
Home-page: https://github.com/pydget/ject
License: MIT
Keywords: function,functional,fp,pipe,pipeline,lambda,noop,signature
Author: Hoyeung Wong
Author-email: hoyeungw@outlook.com
Requires-Python: >=3.8,<4.0
Classifier: License :: OSI Approved :: MIT License
Classifier: Programming Language :: Python :: 3
Classifier: Programming Language :: Python :: 3.8
Project-URL: Repository, https://github.com/pydget/ject
